frago/__init__.py
frago/compat.py
frago/autostart/__init__.py
frago/autostart/base.py
frago/autostart/linux.py
frago/autostart/macos.py
frago/autostart/windows.py
frago/cdp/__init__.py
frago/cdp/client.py
frago/cdp/config.py
frago/cdp/exceptions.py
frago/cdp/logger.py
frago/cdp/retry.py
frago/cdp/session.py
frago/cdp/stealth.js
frago/cdp/types.py
frago/cdp/commands/__init__.py
frago/cdp/commands/chrome.py
frago/cdp/commands/dom.py
frago/cdp/commands/input.py
frago/cdp/commands/page.py
frago/cdp/commands/runtime.py
frago/cdp/commands/screenshot.py
frago/cdp/commands/scroll.py
frago/cdp/commands/status.py
frago/cdp/commands/target.py
frago/cdp/commands/visual_effects.py
frago/cdp/commands/wait.py
frago/cdp/commands/zoom.py
frago/cli/__init__.py
frago/cli/agent_command.py
frago/cli/agent_friendly.py
frago/cli/autostart_command.py
frago/cli/chrome_commands.py
frago/cli/commands.py
frago/cli/init_command.py
frago/cli/main.py
frago/cli/recipe_commands.py
frago/cli/run_commands.py
frago/cli/serve_command.py
frago/cli/server_command.py
frago/cli/session_commands.py
frago/cli/skill_commands.py
frago/cli/start_command.py
frago/cli/sync_command.py
frago/cli/update_command.py
frago/cli/usegit_commands.py
frago/cli/view_command.py
frago/init/__init__.py
frago/init/checker.py
frago/init/config_manager.py
frago/init/configurator.py
frago/init/exceptions.py
frago/init/formatter.py
frago/init/installer.py
frago/init/models.py
frago/init/recovery.py
frago/init/resources.py
frago/init/ui.py
frago/recipes/__init__.py
frago/recipes/env_loader.py
frago/recipes/exceptions.py
frago/recipes/installer.py
frago/recipes/metadata.py
frago/recipes/output_handler.py
frago/recipes/registry.py
frago/recipes/runner.py
frago/resources/__init__.py
frago/resources/commands/frago.agent.md
frago/resources/commands/frago.recipe.md
frago/resources/commands/frago.run.md
frago/resources/commands/frago.skill.md
frago/resources/commands/frago.test.md
frago/resources/commands/frago/COMMON.md
frago_cli-0.39.0.dist-info/METADATA
frago_cli-0.39.0.dist-info/WHEEL
frago_cli-0.39.0.dist-info/entry_points.txt
frago_cli-0.39.0.dist-info/licenses/LICENSE
frago_cli-0.39.0.dist-info/RECORD
