Metadata-Version: 2.4
Name: frago-cli
Version: 0.39.0
Summary: Frago - AI-driven multi-runtime automation framework with Chrome CDP, Python, and Shell support
Project-URL: Homepage, https://frago.ai
Project-URL: Documentation, https://docs.frago.ai
Project-URL: Repository, https://github.com/tsaijamey/frago.git
Project-URL: Issues, https://github.com/tsaijamey/frago/issues
Author-email: Jamey Tsai <caijia@frago.ai>
License: AGPL-3.0-or-later
License-File: LICENSE
Keywords: automation,browser,cdp,chrome,devtools
Classifier: Development Status :: 3 - Alpha
Classifier: Intended Audience :: Developers
Classifier: License :: OSI Approved :: GNU Affero General Public License v3 or later (AGPLv3+)
Classifier: Programming Language :: Python :: 3
Classifier: Programming Language :: Python :: 3.13
Classifier: Topic :: Software Development :: Libraries :: Python Modules
Classifier: Topic :: Software Development :: Testing
Requires-Python: >=3.13
Requires-Dist: arxiv>=2.3.1
Requires-Dist: certifi>=2025.11.12
Requires-Dist: charset-normalizer>=3.4.4
Requires-Dist: click>=8.1.0
Requires-Dist: fastapi>=0.100.0
Requires-Dist: idna>=3.11
Requires-Dist: markdown>=3.4.0
Requires-Dist: obsws-python>=1.8.0
Requires-Dist: psutil>=7.1.3
Requires-Dist: pydantic>=2.0.0
Requires-Dist: pyperclip>=1.8.0
Requires-Dist: pypinyin>=0.51.0
Requires-Dist: python-dotenv>=1.0.0
Requires-Dist: python-frontmatter>=1.0.0
Requires-Dist: python-slugify>=8.0.0
Requires-Dist: pyyaml>=6.0.0
Requires-Dist: questionary>=2.1.0
Requires-Dist: rapidfuzz>=3.0.0
Requires-Dist: requests>=2.32.5
Requires-Dist: urllib3>=2.5.0
Requires-Dist: uvicorn[standard]>=0.23.0
Requires-Dist: watchdog>=3.0.0
Requires-Dist: websocket-client>=1.9.0
Provides-Extra: dev
Requires-Dist: black>=23.0.0; extra == 'dev'
Requires-Dist: isort>=5.12.0; extra == 'dev'
Requires-Dist: mypy>=1.5.0; extra == 'dev'
Requires-Dist: pytest-asyncio>=0.21.0; extra == 'dev'
Requires-Dist: pytest-cov>=4.1.0; extra == 'dev'
Requires-Dist: pytest>=7.4.0; extra == 'dev'
Requires-Dist: ruff>=0.1.0; extra == 'dev'
